{
  "formacion": [
    {
      "date": "2026-05-14",
      "bullets": [
        "CTV OTT Streaming Summit 2026 Londres",
        "Rakuten TV Enterprise Live London",
        "Programmatic Pioneers Summit 2026",
        "DMEXCO 2026"
      ]
    },
    {
      "date": "2026-05-14",
      "bullets": [
        "CTV OTT Streaming Summit 2026 Londres",
        "IAB Europe Academy: Programmatic CTV Certification",
        "Streaming Media Connect 2026",
        "DMEXCO 2026"
      ]
    },
    {
      "date": "2026-05-19",
      "bullets": [
        "Streaming Media Connect 2026",
        "IAB Europe Academy: Programmatic CTV Certification"
      ]
    },
    {
      "date": "2026-05-21",
      "bullets": [
        "StreamTV Show 2026",
        "Banff World Media Festival 2026"
      ]
    },
    {
      "date": "2026-05-25",
      "bullets": [
        "Wurl CTV Trends Report: News Viewers & Brand Safety (descarga gratuita)",
        "EMARKETER Webinar: FAST & the Ad-Supported Streaming Market 2026"
      ]
    },
    {
      "date": "2026-05-26",
      "bullets": [
        "StreamTV Show 2026",
        "IAB Tech Lab CTV Ad Portfolio: Comentario Público Abierto",
        "Banff World Media Festival 2026"
      ]
    }
  ]
}